RPiLEDController/LED.py
RPiLEDController/RPiLEDController.py
RPiLEDController/RPiSupportedVersions.py
RPiLEDController/__init__.py
RPiLEDController-0.1.7.dist-info/METADATA
RPiLEDController-0.1.7.dist-info/WHEEL
RPiLEDController-0.1.7.dist-info/top_level.txt
RPiLEDController-0.1.7.dist-info/RECORD
