Metadata-Version: 2.1
Name: RPiLEDController
Version: 0.1.7
Summary: A library to control the onboard LEDs on a Raspberry Pi
Home-page: UNKNOWN
Author: Paul März
License: UNKNOWN
Keywords: RASPBERRY,PI,LED
Platform: UNKNOWN
